tripp/Clustering.py
tripp/Trajectory.py
tripp/Visualization.py
tripp/__init__.py
tripp/_calculate_charge_center_distances_.py
tripp/_calculate_rmsd_matrix_.py
tripp/_clustering_dbscan_.py
tripp/_clustering_greedy_.py
tripp/_clustering_hdbscan_.py
tripp/_clustering_kmedoids_.py
tripp/_correction_dictionary_.py
tripp/_create_clustering_matrix_.py
tripp/_create_mda_universe_.py
tripp/_density_clustering_utilities_.py
tripp/_determine_charge_center_.py
tripp/_determine_cluster_population_ratio_.py
tripp/_edit_pdb_.py
tripp/_extract_pka_file_data_.py
tripp/_generate_clustering_summary_.py
tripp/_generate_trajectory_log_.py
tripp/_model_pka_values_.py
tripp/_pca_.py
tripp/_pka_iterator_.py
tripp/_propka_input_check_.py
tripp/_pymol_template_.py
tripp/_sort_clusters_.py
tripp/_sort_pka_df_.py
tripp/_write_clustering_info_.py
tripp/analysis.py
tripp-1.1.1.dist-info/LICENSE
tripp-1.1.1.dist-info/METADATA
tripp-1.1.1.dist-info/WHEEL
tripp-1.1.1.dist-info/RECORD
