Metadata-Version: 2.1
Name: tripp
Version: 1.1.1
Summary: Trajectory Iterative pKa Predictor
Author: Christos Matsingos
Author-email: christos.matsingos@u-paris.fr
Requires-Python: >=3.9,<3.10
Classifier: Programming Language :: Python :: 3
Classifier: Programming Language :: Python :: 3.9
Requires-Dist: ipywidgets (>=8.1.7,<9.0.0)
Requires-Dist: mdanalysis (==2.5.0)
Requires-Dist: numpy (==1.25.0)
Requires-Dist: pandas (==2.0.3)
Requires-Dist: pkai (==1.2.0)
Requires-Dist: propka (==3.4.0)
Requires-Dist: pytest (>=8.4.1,<9.0.0)
Requires-Dist: scikit-learn (==1.5.0)
Requires-Dist: scikit-learn-extra (==0.3.0)
Requires-Dist: scipy (==1.13.0)
Requires-Dist: seaborn (==0.13.2)
Requires-Dist: tabulate (==0.9.0)
Requires-Dist: tqdm (>=4.67.1,<5.0.0)
